README.rst
setup.py
snote/__init__.py
snote/codec.py
snote/snote.py
snote.egg-info/PKG-INFO
snote.egg-info/SOURCES.txt
snote.egg-info/dependency_links.txt
snote.egg-info/top_level.txt